[{"line":1,"elements":[{"line":4,"name":"To create job entry with JSON data","description":"","id":"to-create-job-entry-with-json-data","type":"scenario","keyword":"Scenario","steps":[{"name":"url _url","result":{"duration":1111600,"status":"passed"},"match":{"location":"karate","arguments":[]},"keyword":"Given","line":5,"doc_string":{"content_type":"","value":"18:02:35.975 karate.env system property was: staging \n","line":5}},{"name":"path _path","result":{"duration":60626400,"error_message":"js failed:\n>>>>\n01: _path\n<<<<\norg.graalvm.polyglot.PolyglotException: ReferenceError: \"_path\" is not defined\n- <js>.:program(Unnamed:1)\n\nclasspath:com\/api\/automation\/createJobEntry2.feature:6","status":"failed"},"match":{"location":"karate","arguments":[]},"keyword":"And","line":6,"doc_string":{"content_type":"","value":"18:02:36.163 classpath:com\/api\/automation\/createJobEntry2.feature:6\nAnd path _path\njs failed:\n>>>>\n01: _path\n<<<<\norg.graalvm.polyglot.PolyglotException: ReferenceError: \"_path\" is not defined\n- <js>.:program(Unnamed:1)\n\nclasspath:com\/api\/automation\/createJobEntry2.feature:6\n","line":6}},{"name":"request {\"jobId\":'#(_id)',\"jobTitle\":\"Software Engg 3\",\"jobDescription\":\"To develop andriod application\",\"experience\":[\"Google\",\"Apple\",\"Mobile Iron\"],\"project\":[{\"projectName\":\"Movie App\",\"technology\":[\"Kotlin\",\"SQL Lite\",\"Gradle\"]}]},{\"jobId\":2,\"jobTitle\":\"Business Analyst\",\"jobDescription\":\"To develop andriod application\",\"experience\":[\"Google\",\"Apple\",\"Windows\"],\"project\":[{\"projectName\":\"Movie App\",\"technology\":[\"Kotlin\",\"SQL Lite\",\"Selenium\"]}]}","result":{"duration":0,"status":"skipped"},"match":{"location":"karate","arguments":[]},"keyword":"And","line":8},{"name":"headers {Accept : 'application\/json',Content-Type : 'application\/json'}","result":{"duration":0,"status":"skipped"},"match":{"location":"karate","arguments":[]},"keyword":"And","line":9},{"name":"method post","result":{"duration":0,"status":"skipped"},"match":{"location":"karate","arguments":[]},"keyword":"When","line":10},{"name":"status 201","result":{"duration":0,"status":"skipped"},"match":{"location":"karate","arguments":[]},"keyword":"Then","line":11}],"tags":[]}],"name":"com\/api\/automation\/createJobEntry2.feature","description":"To create job entry in the application\nUse Post \/normal\/webapi\/add to create job entry in the application","id":"to-create-job-entry-in-the-application","keyword":"Feature","uri":"com\/api\/automation\/createJobEntry2.feature"}]